nebu/__init__.py
nebu/_version.py
nebu/config.py
nebu/logger.py
nebu/utils.py
nebu/cli/__init__.py
nebu/cli/_common.py
nebu/cli/assemble.py
nebu/cli/atom.py
nebu/cli/environment.py
nebu/cli/exceptions.py
nebu/cli/get.py
nebu/cli/main.py
nebu/cli/ping.py
nebu/cli/publish.py
nebu/cli/session.py
nebu/cli/validate.py
nebu/models/__init__.py
nebu/models/binder.py
nebu/models/document.py
nebu/models/resource.py
nebu/models/utils.py
nebu/tests/__init__.py
nebu/tests/conftest.py
nebu/tests/test_config.py
nebu/tests/test_utils.py
nebu/tests/cli/__init__.py
nebu/tests/cli/test__common.py
nebu/tests/cli/test_assemble.py
nebu/tests/cli/test_atom.py
nebu/tests/cli/test_environment.py
nebu/tests/cli/test_get.py
nebu/tests/cli/test_main.py
nebu/tests/cli/test_ping.py
nebu/tests/cli/test_publish.py
nebu/tests/cli/test_validate.py
nebu/tests/cli/scanned_import/__init__.py
nebu/tests/cli/scanned_import/module1.py
nebu/tests/cli/scanned_import/module2.py
nebu/tests/data/assembled_collection_for_bakedpdf_workflow/README.md
nebu/tests/data/assembled_collection_for_bakedpdf_workflow/collection.assembled.xhtml
nebu/tests/data/assembled_collection_for_bakedpdf_workflow/m46882.xhtml
nebu/tests/data/assembled_collection_for_bakedpdf_workflow/m46909.xhtml
nebu/tests/data/assembled_collection_for_bakedpdf_workflow/m46913.xhtml
nebu/tests/data/assembled_collection_for_bakedpdf_workflow/rebuild.py
nebu/tests/data/assembled_collection_for_git_workflow/README.md
nebu/tests/data/assembled_collection_for_git_workflow/collection.assembled.xhtml
nebu/tests/data/assembled_collection_for_git_workflow/m46882.xhtml
nebu/tests/data/assembled_collection_for_git_workflow/m46909.xhtml
nebu/tests/data/assembled_collection_for_git_workflow/m46913.xhtml
nebu/tests/data/assembled_collection_for_git_workflow/rebuild.py
nebu/tests/data/collection/collection.xml
nebu/tests/data/collection/metadata.json
nebu/tests/data/collection_for_bakedpdf_workflow/README.md
nebuchadnezzar-9.13.1.dist-info/LICENSE.txt
nebuchadnezzar-9.13.1.dist-info/METADATA
nebuchadnezzar-9.13.1.dist-info/WHEEL
nebuchadnezzar-9.13.1.dist-info/entry_points.txt
nebuchadnezzar-9.13.1.dist-info/top_level.txt
nebuchadnezzar-9.13.1.dist-info/RECORD
