Metadata-Version: 2.1
Name: nebuchadnezzar
Version: 9.13.1
Summary: OpenStax Nebu publishing utility
Home-page: https://github.com/openstax/nebuchadnezzar
Author: OpenStax team
Author-email: info@cnx.org
License: AGPL, See also LICENSE.txt
Platform: UNKNOWN
License-File: LICENSE.txt
Requires-Dist: lxml (==4.4.3)
Requires-Dist: click (>=7.1.2)
Requires-Dist: cnxml (>=3.1.7)
Requires-Dist: cnx-epub (>=0.31.2)
Requires-Dist: cnx-litezip (>=1.6.0)
Requires-Dist: cnx-transforms (>=1.7.0)
Requires-Dist: docker (>=4.2.2)
Requires-Dist: pip
Requires-Dist: requests (>=2.24.0)
Requires-Dist: setuptools
Requires-Dist: aiohttp[speedups] (>=3.6.2)
Requires-Dist: backoff (==1.11.1)
Provides-Extra: tasks
Requires-Dist: neb-tasks ; extra == 'tasks'
Provides-Extra: test
Requires-Dist: pretend ; extra == 'test'
Requires-Dist: pytest (>=4.6) ; extra == 'test'
Requires-Dist: pytest-cov ; extra == 'test'
Requires-Dist: pytest-runner ; extra == 'test'
Requires-Dist: requests-mock ; extra == 'test'
Requires-Dist: aioresponses ; extra == 'test'
